deepomatic/rpc/buffers/__init__.py
deepomatic/rpc/buffers/protobuf/__init__.py
deepomatic/rpc/buffers/protobuf/cli/Message_pb2.py
deepomatic/rpc/buffers/protobuf/cli/Message_pb2.pyi
deepomatic/rpc/buffers/protobuf/cli/Message_pb2_grpc.py
deepomatic/rpc/buffers/protobuf/cli/__init__.py
deepomatic/rpc/buffers/protobuf/common/Error_pb2.py
deepomatic/rpc/buffers/protobuf/common/Error_pb2.pyi
deepomatic/rpc/buffers/protobuf/common/Error_pb2_grpc.py
deepomatic/rpc/buffers/protobuf/common/Image_pb2.py
deepomatic/rpc/buffers/protobuf/common/Image_pb2.pyi
deepomatic/rpc/buffers/protobuf/common/Image_pb2_grpc.py
deepomatic/rpc/buffers/protobuf/common/__init__.py
deepomatic/rpc/buffers/protobuf/nn/Command_pb2.py
deepomatic/rpc/buffers/protobuf/nn/Command_pb2.pyi
deepomatic/rpc/buffers/protobuf/nn/Command_pb2_grpc.py
deepomatic/rpc/buffers/protobuf/nn/Message_pb2.py
deepomatic/rpc/buffers/protobuf/nn/Message_pb2.pyi
deepomatic/rpc/buffers/protobuf/nn/Message_pb2_grpc.py
deepomatic/rpc/buffers/protobuf/nn/Postprocessing_pb2.py
deepomatic/rpc/buffers/protobuf/nn/Postprocessing_pb2.pyi
deepomatic/rpc/buffers/protobuf/nn/Postprocessing_pb2_grpc.py
deepomatic/rpc/buffers/protobuf/nn/Preprocessing_pb2.py
deepomatic/rpc/buffers/protobuf/nn/Preprocessing_pb2.pyi
deepomatic/rpc/buffers/protobuf/nn/Preprocessing_pb2_grpc.py
deepomatic/rpc/buffers/protobuf/nn/Result_pb2.py
deepomatic/rpc/buffers/protobuf/nn/Result_pb2.pyi
deepomatic/rpc/buffers/protobuf/nn/Result_pb2_grpc.py
deepomatic/rpc/buffers/protobuf/nn/__init__.py
deepomatic/rpc/buffers/protobuf/nn/frameworks/Caffe_pb2.py
deepomatic/rpc/buffers/protobuf/nn/frameworks/Caffe_pb2.pyi
deepomatic/rpc/buffers/protobuf/nn/frameworks/Caffe_pb2_grpc.py
deepomatic/rpc/buffers/protobuf/nn/frameworks/__init__.py
deepomatic/rpc/buffers/protobuf/nn/v07/Commands_pb2.py
deepomatic/rpc/buffers/protobuf/nn/v07/Commands_pb2.pyi
deepomatic/rpc/buffers/protobuf/nn/v07/Commands_pb2_grpc.py
deepomatic/rpc/buffers/protobuf/nn/v07/Inputs_pb2.py
deepomatic_rpc_protobuf-3.29.0.dist-info/licenses/LICENCE
deepomatic_rpc_protobuf-3.29.0.dist-info/METADATA
deepomatic_rpc_protobuf-3.29.0.dist-info/WHEEL
deepomatic_rpc_protobuf-3.29.0.dist-info/top_level.txt
deepomatic_rpc_protobuf-3.29.0.dist-info/RECORD
