Metadata-Version: 2.4
Name: deepomatic-rpc-protobuf
Version: 3.29.0
Summary: Generated protobufs for deepomatic-rpc
Author-email: deepomatic <support@deepomatic.com>
Project-URL: Homepage, https://github.com/Deepomatic/deepomatic-rpc
Project-URL: Company, https://www.deepomatic.com
Classifier: Programming Language :: Python :: 3.9
Classifier: Programming Language :: Python :: 3
Classifier: Operating System :: OS Independent
Requires-Python: >=3.7
License-File: LICENCE
Requires-Dist: protobuf~=5.29
Dynamic: license-file
